autoapply/__init__.py
autoapply/autoapply.py
autoapply/helper/__init__.py
autoapply/helper/excel_handler.py
autoapply/helper/genai.py
autoapply/helper/gotolink.py
autoapply/helper/gui.py
autoapply/helper/pdfhandler.py
autoply-1.0.1.dist-info/METADATA
autoply-1.0.1.dist-info/WHEEL
autoply-1.0.1.dist-info/top_level.txt
autoply-1.0.1.dist-info/RECORD
