Metadata-Version: 2.1
Name: autoply
Version: 1.0.1
Summary: Just as the name implies, auto apply on wellfound with a custom cover letter for every role. Sit back and let AI help you get the job :)
Author: ['Anupam Maurya', 'Chaitanya Anand']
Author-email: ['anupammaurya981@gmail.com']
License: MIT
Classifier: Development Status :: 3 - Alpha
Classifier: Intended Audience :: Developers
Classifier: Topic :: Software Development :: Build Tools
Classifier: Programming Language :: Python :: 3.11
Requires-Python: >=3.11
Requires-Dist: selenium
Requires-Dist: tk
Requires-Dist: python-dotenv
Requires-Dist: google-generativeai
Requires-Dist: webdriver-manager
Requires-Dist: PyPDF2
Requires-Dist: openpyxl
